{
  "generatedAt": "2026-06-05T16:12:11.255Z",
  "totalDraws": 977,
  "windowSize": null,
  "decayFactor": 0.97,
  "data": [
    {
      "combo": [
        7,
        26
      ],
      "count": 22,
      "weightedScore": 2.5021884374592953,
      "gap": 0,
      "lastSeenTerm": "115000137"
    },
    {
      "combo": [
        8,
        35
      ],
      "count": 16,
      "weightedScore": 2.3056689869784863,
      "gap": 1,
      "lastSeenTerm": "115000136"
    },
    {
      "combo": [
        2,
        3
      ],
      "count": 14,
      "weightedScore": 2.0942554635055552,
      "gap": 5,
      "lastSeenTerm": "115000132"
    },
    {
      "combo": [
        25,
        36
      ],
      "count": 19,
      "weightedScore": 2.00768833828917,
      "gap": 13,
      "lastSeenTerm": "115000124"
    },
    {
      "combo": [
        2,
        8
      ],
      "count": 13,
      "weightedScore": 1.9980048741418202,
      "gap": 1,
      "lastSeenTerm": "115000136"
    },
    {
      "combo": [
        6,
        31
      ],
      "count": 16,
      "weightedScore": 1.9630349691856845,
      "gap": 7,
      "lastSeenTerm": "115000130"
    },
    {
      "combo": [
        17,
        25
      ],
      "count": 14,
      "weightedScore": 1.9032806457478495,
      "gap": 2,
      "lastSeenTerm": "115000135"
    },
    {
      "combo": [
        22,
        26
      ],
      "count": 16,
      "weightedScore": 1.866949726784204,
      "gap": 3,
      "lastSeenTerm": "115000134"
    },
    {
      "combo": [
        6,
        12
      ],
      "count": 11,
      "weightedScore": 1.8184912075055948,
      "gap": 7,
      "lastSeenTerm": "115000130"
    },
    {
      "combo": [
        6,
        9
      ],
      "count": 12,
      "weightedScore": 1.7838069235996965,
      "gap": 7,
      "lastSeenTerm": "115000130"
    },
    {
      "combo": [
        2,
        11
      ],
      "count": 15,
      "weightedScore": 1.7774833893646167,
      "gap": 9,
      "lastSeenTerm": "115000128"
    },
    {
      "combo": [
        8,
        38
      ],
      "count": 13,
      "weightedScore": 1.7618549727315735,
      "gap": 2,
      "lastSeenTerm": "115000135"
    },
    {
      "combo": [
        8,
        25
      ],
      "count": 15,
      "weightedScore": 1.7355104459993451,
      "gap": 2,
      "lastSeenTerm": "115000135"
    },
    {
      "combo": [
        7,
        31
      ],
      "count": 12,
      "weightedScore": 1.7352393496928522,
      "gap": 0,
      "lastSeenTerm": "115000137"
    },
    {
      "combo": [
        8,
        24
      ],
      "count": 14,
      "weightedScore": 1.6350727474602778,
      "gap": 1,
      "lastSeenTerm": "115000136"
    },
    {
      "combo": [
        6,
        36
      ],
      "count": 18,
      "weightedScore": 1.6175145203023724,
      "gap": 10,
      "lastSeenTerm": "115000127"
    },
    {
      "combo": [
        25,
        38
      ],
      "count": 13,
      "weightedScore": 1.5995541458201907,
      "gap": 2,
      "lastSeenTerm": "115000135"
    },
    {
      "combo": [
        2,
        7
      ],
      "count": 12,
      "weightedScore": 1.5823327231713815,
      "gap": 9,
      "lastSeenTerm": "115000128"
    },
    {
      "combo": [
        2,
        29
      ],
      "count": 18,
      "weightedScore": 1.5467601318244422,
      "gap": 1,
      "lastSeenTerm": "115000136"
    },
    {
      "combo": [
        21,
        27
      ],
      "count": 14,
      "weightedScore": 1.5259323524059412,
      "gap": 0,
      "lastSeenTerm": "115000137"
    },
    {
      "combo": [
        2,
        25
      ],
      "count": 11,
      "weightedScore": 1.5127502358604654,
      "gap": 2,
      "lastSeenTerm": "115000135"
    },
    {
      "combo": [
        9,
        25
      ],
      "count": 11,
      "weightedScore": 1.5116536943683023,
      "gap": 13,
      "lastSeenTerm": "115000124"
    },
    {
      "combo": [
        20,
        35
      ],
      "count": 13,
      "weightedScore": 1.4859471086317302,
      "gap": 6,
      "lastSeenTerm": "115000131"
    },
    {
      "combo": [
        8,
        17
      ],
      "count": 14,
      "weightedScore": 1.4803280747890804,
      "gap": 2,
      "lastSeenTerm": "115000135"
    },
    {
      "combo": [
        18,
        21
      ],
      "count": 11,
      "weightedScore": 1.4694446196903144,
      "gap": 8,
      "lastSeenTerm": "115000129"
    },
    {
      "combo": [
        12,
        22
      ],
      "count": 15,
      "weightedScore": 1.4615782827096868,
      "gap": 3,
      "lastSeenTerm": "115000134"
    },
    {
      "combo": [
        8,
        15
      ],
      "count": 12,
      "weightedScore": 1.4581160740652042,
      "gap": 12,
      "lastSeenTerm": "115000125"
    },
    {
      "combo": [
        2,
        13
      ],
      "count": 23,
      "weightedScore": 1.4565637670781113,
      "gap": 5,
      "lastSeenTerm": "115000132"
    },
    {
      "combo": [
        15,
        20
      ],
      "count": 15,
      "weightedScore": 1.4479271169699923,
      "gap": 6,
      "lastSeenTerm": "115000131"
    },
    {
      "combo": [
        14,
        20
      ],
      "count": 23,
      "weightedScore": 1.4444763269752592,
      "gap": 4,
      "lastSeenTerm": "115000133"
    },
    {
      "combo": [
        12,
        26
      ],
      "count": 15,
      "weightedScore": 1.441759683689759,
      "gap": 3,
      "lastSeenTerm": "115000134"
    },
    {
      "combo": [
        15,
        16
      ],
      "count": 9,
      "weightedScore": 1.4250282471092968,
      "gap": 11,
      "lastSeenTerm": "115000126"
    },
    {
      "combo": [
        2,
        35
      ],
      "count": 14,
      "weightedScore": 1.4145727502497734,
      "gap": 1,
      "lastSeenTerm": "115000136"
    },
    {
      "combo": [
        27,
        31
      ],
      "count": 21,
      "weightedScore": 1.4004853583884564,
      "gap": 0,
      "lastSeenTerm": "115000137"
    },
    {
      "combo": [
        7,
        12
      ],
      "count": 20,
      "weightedScore": 1.3994261546938422,
      "gap": 3,
      "lastSeenTerm": "115000134"
    },
    {
      "combo": [
        19,
        28
      ],
      "count": 17,
      "weightedScore": 1.391952548209197,
      "gap": 4,
      "lastSeenTerm": "115000133"
    },
    {
      "combo": [
        2,
        21
      ],
      "count": 17,
      "weightedScore": 1.3910112015327751,
      "gap": 8,
      "lastSeenTerm": "115000129"
    },
    {
      "combo": [
        8,
        20
      ],
      "count": 15,
      "weightedScore": 1.3739980369047693,
      "gap": 16,
      "lastSeenTerm": "115000121"
    },
    {
      "combo": [
        7,
        21
      ],
      "count": 11,
      "weightedScore": 1.3678543954265712,
      "gap": 0,
      "lastSeenTerm": "115000137"
    },
    {
      "combo": [
        17,
        38
      ],
      "count": 9,
      "weightedScore": 1.36665323767333,
      "gap": 2,
      "lastSeenTerm": "115000135"
    },
    {
      "combo": [
        6,
        24
      ],
      "count": 20,
      "weightedScore": 1.359850562375454,
      "gap": 11,
      "lastSeenTerm": "115000126"
    },
    {
      "combo": [
        21,
        35
      ],
      "count": 18,
      "weightedScore": 1.321383782349601,
      "gap": 14,
      "lastSeenTerm": "115000123"
    },
    {
      "combo": [
        4,
        39
      ],
      "count": 9,
      "weightedScore": 1.3170490417996998,
      "gap": 5,
      "lastSeenTerm": "115000132"
    },
    {
      "combo": [
        1,
        23
      ],
      "count": 7,
      "weightedScore": 1.305882659776266,
      "gap": 14,
      "lastSeenTerm": "115000123"
    },
    {
      "combo": [
        2,
        37
      ],
      "count": 17,
      "weightedScore": 1.301065389211797,
      "gap": 9,
      "lastSeenTerm": "115000128"
    },
    {
      "combo": [
        13,
        36
      ],
      "count": 17,
      "weightedScore": 1.29782217302036,
      "gap": 18,
      "lastSeenTerm": "115000119"
    },
    {
      "combo": [
        24,
        35
      ],
      "count": 16,
      "weightedScore": 1.2958986377659931,
      "gap": 1,
      "lastSeenTerm": "115000136"
    },
    {
      "combo": [
        36,
        37
      ],
      "count": 24,
      "weightedScore": 1.2904391019538497,
      "gap": 10,
      "lastSeenTerm": "115000127"
    },
    {
      "combo": [
        2,
        17
      ],
      "count": 20,
      "weightedScore": 1.2902361121166475,
      "gap": 2,
      "lastSeenTerm": "115000135"
    },
    {
      "combo": [
        26,
        31
      ],
      "count": 9,
      "weightedScore": 1.2896673962879863,
      "gap": 0,
      "lastSeenTerm": "115000137"
    },
    {
      "combo": [
        18,
        19
      ],
      "count": 18,
      "weightedScore": 1.2887885466146445,
      "gap": 8,
      "lastSeenTerm": "115000129"
    },
    {
      "combo": [
        32,
        33
      ],
      "count": 14,
      "weightedScore": 1.2868046908111879,
      "gap": 16,
      "lastSeenTerm": "115000121"
    },
    {
      "combo": [
        8,
        16
      ],
      "count": 14,
      "weightedScore": 1.2851519604122257,
      "gap": 12,
      "lastSeenTerm": "115000125"
    },
    {
      "combo": [
        8,
        29
      ],
      "count": 12,
      "weightedScore": 1.268794136610004,
      "gap": 1,
      "lastSeenTerm": "115000136"
    },
    {
      "combo": [
        3,
        13
      ],
      "count": 18,
      "weightedScore": 1.266045351178973,
      "gap": 5,
      "lastSeenTerm": "115000132"
    },
    {
      "combo": [
        24,
        29
      ],
      "count": 11,
      "weightedScore": 1.2631498955719147,
      "gap": 1,
      "lastSeenTerm": "115000136"
    },
    {
      "combo": [
        3,
        21
      ],
      "count": 23,
      "weightedScore": 1.262332776514174,
      "gap": 8,
      "lastSeenTerm": "115000129"
    },
    {
      "combo": [
        16,
        24
      ],
      "count": 10,
      "weightedScore": 1.24430281590799,
      "gap": 11,
      "lastSeenTerm": "115000126"
    },
    {
      "combo": [
        6,
        32
      ],
      "count": 16,
      "weightedScore": 1.2413709432866726,
      "gap": 15,
      "lastSeenTerm": "115000122"
    },
    {
      "combo": [
        14,
        28
      ],
      "count": 16,
      "weightedScore": 1.2318079077833826,
      "gap": 4,
      "lastSeenTerm": "115000133"
    },
    {
      "combo": [
        1,
        36
      ],
      "count": 13,
      "weightedScore": 1.2274787444628539,
      "gap": 18,
      "lastSeenTerm": "115000119"
    },
    {
      "combo": [
        21,
        31
      ],
      "count": 11,
      "weightedScore": 1.2097980430221236,
      "gap": 0,
      "lastSeenTerm": "115000137"
    },
    {
      "combo": [
        2,
        38
      ],
      "count": 14,
      "weightedScore": 1.1949173619083218,
      "gap": 2,
      "lastSeenTerm": "115000135"
    },
    {
      "combo": [
        12,
        30
      ],
      "count": 15,
      "weightedScore": 1.1939925790126218,
      "gap": 3,
      "lastSeenTerm": "115000134"
    },
    {
      "combo": [
        15,
        38
      ],
      "count": 17,
      "weightedScore": 1.191699825009719,
      "gap": 11,
      "lastSeenTerm": "115000126"
    },
    {
      "combo": [
        8,
        18
      ],
      "count": 13,
      "weightedScore": 1.191471954754956,
      "gap": 19,
      "lastSeenTerm": "115000118"
    },
    {
      "combo": [
        2,
        14
      ],
      "count": 12,
      "weightedScore": 1.1846205209201681,
      "gap": 9,
      "lastSeenTerm": "115000128"
    },
    {
      "combo": [
        5,
        20
      ],
      "count": 12,
      "weightedScore": 1.1810429153575244,
      "gap": 4,
      "lastSeenTerm": "115000133"
    },
    {
      "combo": [
        8,
        37
      ],
      "count": 14,
      "weightedScore": 1.174560369305861,
      "gap": 12,
      "lastSeenTerm": "115000125"
    },
    {
      "combo": [
        2,
        4
      ],
      "count": 15,
      "weightedScore": 1.1689886567862289,
      "gap": 5,
      "lastSeenTerm": "115000132"
    },
    {
      "combo": [
        3,
        4
      ],
      "count": 15,
      "weightedScore": 1.1686313916212163,
      "gap": 5,
      "lastSeenTerm": "115000132"
    },
    {
      "combo": [
        2,
        6
      ],
      "count": 12,
      "weightedScore": 1.1665510685228413,
      "gap": 20,
      "lastSeenTerm": "115000117"
    },
    {
      "combo": [
        6,
        15
      ],
      "count": 10,
      "weightedScore": 1.1641408041945518,
      "gap": 11,
      "lastSeenTerm": "115000126"
    },
    {
      "combo": [
        8,
        27
      ],
      "count": 21,
      "weightedScore": 1.158549492288071,
      "gap": 27,
      "lastSeenTerm": "115000110"
    },
    {
      "combo": [
        3,
        20
      ],
      "count": 17,
      "weightedScore": 1.1409336353710573,
      "gap": 30,
      "lastSeenTerm": "115000107"
    },
    {
      "combo": [
        20,
        21
      ],
      "count": 20,
      "weightedScore": 1.1381519876822455,
      "gap": 14,
      "lastSeenTerm": "115000123"
    },
    {
      "combo": [
        16,
        37
      ],
      "count": 16,
      "weightedScore": 1.1332248593042626,
      "gap": 12,
      "lastSeenTerm": "115000125"
    },
    {
      "combo": [
        1,
        25
      ],
      "count": 11,
      "weightedScore": 1.115509396130747,
      "gap": 18,
      "lastSeenTerm": "115000119"
    },
    {
      "combo": [
        29,
        35
      ],
      "count": 13,
      "weightedScore": 1.1131392253702417,
      "gap": 1,
      "lastSeenTerm": "115000136"
    },
    {
      "combo": [
        1,
        26
      ],
      "count": 13,
      "weightedScore": 1.1113910144416146,
      "gap": 21,
      "lastSeenTerm": "115000116"
    },
    {
      "combo": [
        5,
        36
      ],
      "count": 14,
      "weightedScore": 1.1092716907198834,
      "gap": 10,
      "lastSeenTerm": "115000127"
    },
    {
      "combo": [
        21,
        25
      ],
      "count": 13,
      "weightedScore": 1.1058709182548125,
      "gap": 23,
      "lastSeenTerm": "115000114"
    },
    {
      "combo": [
        4,
        8
      ],
      "count": 13,
      "weightedScore": 1.0835810186031885,
      "gap": 12,
      "lastSeenTerm": "115000125"
    },
    {
      "combo": [
        26,
        27
      ],
      "count": 12,
      "weightedScore": 1.0778134748869945,
      "gap": 0,
      "lastSeenTerm": "115000137"
    },
    {
      "combo": [
        12,
        31
      ],
      "count": 15,
      "weightedScore": 1.0757678979889642,
      "gap": 7,
      "lastSeenTerm": "115000130"
    },
    {
      "combo": [
        3,
        39
      ],
      "count": 16,
      "weightedScore": 1.0689699975804103,
      "gap": 5,
      "lastSeenTerm": "115000132"
    },
    {
      "combo": [
        2,
        32
      ],
      "count": 14,
      "weightedScore": 1.0625999933003367,
      "gap": 17,
      "lastSeenTerm": "115000120"
    },
    {
      "combo": [
        25,
        34
      ],
      "count": 19,
      "weightedScore": 1.058248932195204,
      "gap": 13,
      "lastSeenTerm": "115000124"
    },
    {
      "combo": [
        7,
        22
      ],
      "count": 18,
      "weightedScore": 1.0571610725790541,
      "gap": 3,
      "lastSeenTerm": "115000134"
    },
    {
      "combo": [
        18,
        28
      ],
      "count": 16,
      "weightedScore": 1.056339859554556,
      "gap": 19,
      "lastSeenTerm": "115000118"
    },
    {
      "combo": [
        20,
        28
      ],
      "count": 18,
      "weightedScore": 1.0485881451616028,
      "gap": 4,
      "lastSeenTerm": "115000133"
    },
    {
      "combo": [
        12,
        15
      ],
      "count": 20,
      "weightedScore": 1.045750534414718,
      "gap": 6,
      "lastSeenTerm": "115000131"
    },
    {
      "combo": [
        24,
        38
      ],
      "count": 16,
      "weightedScore": 1.0427354605112065,
      "gap": 11,
      "lastSeenTerm": "115000126"
    },
    {
      "combo": [
        14,
        19
      ],
      "count": 17,
      "weightedScore": 1.0235651107243218,
      "gap": 4,
      "lastSeenTerm": "115000133"
    },
    {
      "combo": [
        12,
        35
      ],
      "count": 20,
      "weightedScore": 1.0233143240244769,
      "gap": 6,
      "lastSeenTerm": "115000131"
    },
    {
      "combo": [
        2,
        24
      ],
      "count": 11,
      "weightedScore": 1.0151624139437843,
      "gap": 1,
      "lastSeenTerm": "115000136"
    },
    {
      "combo": [
        20,
        23
      ],
      "count": 14,
      "weightedScore": 1.0138169720911199,
      "gap": 14,
      "lastSeenTerm": "115000123"
    },
    {
      "combo": [
        7,
        27
      ],
      "count": 11,
      "weightedScore": 1.0009271489697067,
      "gap": 0,
      "lastSeenTerm": "115000137"
    },
    {
      "combo": [
        21,
        26
      ],
      "count": 14,
      "weightedScore": 1.0006530040312653,
      "gap": 0,
      "lastSeenTerm": "115000137"
    },
    {
      "combo": [
        8,
        39
      ],
      "count": 10,
      "weightedScore": 0.9961002289740573,
      "gap": 19,
      "lastSeenTerm": "115000118"
    },
    {
      "combo": [
        34,
        35
      ],
      "count": 16,
      "weightedScore": 0.9938452872615704,
      "gap": 6,
      "lastSeenTerm": "115000131"
    },
    {
      "combo": [
        5,
        28
      ],
      "count": 16,
      "weightedScore": 0.9919706546740211,
      "gap": 4,
      "lastSeenTerm": "115000133"
    },
    {
      "combo": [
        19,
        21
      ],
      "count": 18,
      "weightedScore": 0.9901630041222504,
      "gap": 8,
      "lastSeenTerm": "115000129"
    },
    {
      "combo": [
        5,
        37
      ],
      "count": 16,
      "weightedScore": 0.9899106598903791,
      "gap": 10,
      "lastSeenTerm": "115000127"
    },
    {
      "combo": [
        18,
        25
      ],
      "count": 10,
      "weightedScore": 0.9857030982173551,
      "gap": 23,
      "lastSeenTerm": "115000114"
    },
    {
      "combo": [
        15,
        34
      ],
      "count": 15,
      "weightedScore": 0.9825724699333445,
      "gap": 6,
      "lastSeenTerm": "115000131"
    },
    {
      "combo": [
        7,
        11
      ],
      "count": 23,
      "weightedScore": 0.9755121071217219,
      "gap": 9,
      "lastSeenTerm": "115000128"
    },
    {
      "combo": [
        5,
        6
      ],
      "count": 10,
      "weightedScore": 0.9677983535850655,
      "gap": 10,
      "lastSeenTerm": "115000127"
    },
    {
      "combo": [
        21,
        22
      ],
      "count": 15,
      "weightedScore": 0.9672259217418433,
      "gap": 23,
      "lastSeenTerm": "115000114"
    },
    {
      "combo": [
        20,
        33
      ],
      "count": 11,
      "weightedScore": 0.9612229860401398,
      "gap": 16,
      "lastSeenTerm": "115000121"
    },
    {
      "combo": [
        20,
        34
      ],
      "count": 15,
      "weightedScore": 0.9497847032559616,
      "gap": 6,
      "lastSeenTerm": "115000131"
    },
    {
      "combo": [
        19,
        20
      ],
      "count": 9,
      "weightedScore": 0.9491762444674795,
      "gap": 4,
      "lastSeenTerm": "115000133"
    },
    {
      "combo": [
        26,
        30
      ],
      "count": 11,
      "weightedScore": 0.9430680465851046,
      "gap": 3,
      "lastSeenTerm": "115000134"
    },
    {
      "combo": [
        23,
        35
      ],
      "count": 10,
      "weightedScore": 0.9384817391065188,
      "gap": 14,
      "lastSeenTerm": "115000123"
    },
    {
      "combo": [
        28,
        36
      ],
      "count": 11,
      "weightedScore": 0.9375425976440926,
      "gap": 13,
      "lastSeenTerm": "115000124"
    },
    {
      "combo": [
        4,
        13
      ],
      "count": 7,
      "weightedScore": 0.9367786453982998,
      "gap": 5,
      "lastSeenTerm": "115000132"
    },
    {
      "combo": [
        22,
        30
      ],
      "count": 14,
      "weightedScore": 0.9318992772347301,
      "gap": 3,
      "lastSeenTerm": "115000134"
    },
    {
      "combo": [
        7,
        30
      ],
      "count": 16,
      "weightedScore": 0.9262185469284497,
      "gap": 3,
      "lastSeenTerm": "115000134"
    },
    {
      "combo": [
        8,
        32
      ],
      "count": 14,
      "weightedScore": 0.9239695586739698,
      "gap": 16,
      "lastSeenTerm": "115000121"
    },
    {
      "combo": [
        8,
        21
      ],
      "count": 14,
      "weightedScore": 0.9219466392511959,
      "gap": 33,
      "lastSeenTerm": "115000104"
    },
    {
      "combo": [
        14,
        37
      ],
      "count": 9,
      "weightedScore": 0.9212951801462722,
      "gap": 9,
      "lastSeenTerm": "115000128"
    },
    {
      "combo": [
        22,
        36
      ],
      "count": 13,
      "weightedScore": 0.9208428972965512,
      "gap": 28,
      "lastSeenTerm": "115000109"
    },
    {
      "combo": [
        12,
        20
      ],
      "count": 18,
      "weightedScore": 0.9200888993468821,
      "gap": 6,
      "lastSeenTerm": "115000131"
    },
    {
      "combo": [
        2,
        36
      ],
      "count": 16,
      "weightedScore": 0.9129662119687845,
      "gap": 22,
      "lastSeenTerm": "115000115"
    },
    {
      "combo": [
        5,
        14
      ],
      "count": 16,
      "weightedScore": 0.9128660556432661,
      "gap": 4,
      "lastSeenTerm": "115000133"
    },
    {
      "combo": [
        7,
        14
      ],
      "count": 19,
      "weightedScore": 0.9056964259820741,
      "gap": 9,
      "lastSeenTerm": "115000128"
    },
    {
      "combo": [
        6,
        16
      ],
      "count": 10,
      "weightedScore": 0.9026235792385222,
      "gap": 11,
      "lastSeenTerm": "115000126"
    },
    {
      "combo": [
        5,
        19
      ],
      "count": 9,
      "weightedScore": 0.9001552594576704,
      "gap": 4,
      "lastSeenTerm": "115000133"
    },
    {
      "combo": [
        12,
        36
      ],
      "count": 15,
      "weightedScore": 0.8946112358620513,
      "gap": 10,
      "lastSeenTerm": "115000127"
    },
    {
      "combo": [
        2,
        19
      ],
      "count": 12,
      "weightedScore": 0.8924269705354271,
      "gap": 8,
      "lastSeenTerm": "115000129"
    },
    {
      "combo": [
        9,
        31
      ],
      "count": 14,
      "weightedScore": 0.8905981673743133,
      "gap": 7,
      "lastSeenTerm": "115000130"
    },
    {
      "combo": [
        1,
        21
      ],
      "count": 12,
      "weightedScore": 0.8898883520498709,
      "gap": 14,
      "lastSeenTerm": "115000123"
    },
    {
      "combo": [
        5,
        12
      ],
      "count": 16,
      "weightedScore": 0.8882519822554997,
      "gap": 10,
      "lastSeenTerm": "115000127"
    },
    {
      "combo": [
        4,
        31
      ],
      "count": 10,
      "weightedScore": 0.8872499851933554,
      "gap": 15,
      "lastSeenTerm": "115000122"
    },
    {
      "combo": [
        24,
        31
      ],
      "count": 19,
      "weightedScore": 0.8845356168186436,
      "gap": 15,
      "lastSeenTerm": "115000122"
    },
    {
      "combo": [
        18,
        23
      ],
      "count": 12,
      "weightedScore": 0.8723777686137992,
      "gap": 24,
      "lastSeenTerm": "115000113"
    },
    {
      "combo": [
        11,
        14
      ],
      "count": 17,
      "weightedScore": 0.8659260926850032,
      "gap": 9,
      "lastSeenTerm": "115000128"
    },
    {
      "combo": [
        15,
        35
      ],
      "count": 9,
      "weightedScore": 0.862197090159757,
      "gap": 6,
      "lastSeenTerm": "115000131"
    },
    {
      "combo": [
        2,
        39
      ],
      "count": 9,
      "weightedScore": 0.8593480882746929,
      "gap": 5,
      "lastSeenTerm": "115000132"
    },
    {
      "combo": [
        13,
        39
      ],
      "count": 10,
      "weightedScore": 0.8587845270902769,
      "gap": 5,
      "lastSeenTerm": "115000132"
    },
    {
      "combo": [
        12,
        34
      ],
      "count": 13,
      "weightedScore": 0.8539260439499369,
      "gap": 6,
      "lastSeenTerm": "115000131"
    },
    {
      "combo": [
        4,
        6
      ],
      "count": 11,
      "weightedScore": 0.8525448379946752,
      "gap": 15,
      "lastSeenTerm": "115000122"
    },
    {
      "combo": [
        6,
        19
      ],
      "count": 15,
      "weightedScore": 0.8415405433290795,
      "gap": 7,
      "lastSeenTerm": "115000130"
    },
    {
      "combo": [
        6,
        37
      ],
      "count": 19,
      "weightedScore": 0.8376899301391056,
      "gap": 10,
      "lastSeenTerm": "115000127"
    },
    {
      "combo": [
        15,
        37
      ],
      "count": 17,
      "weightedScore": 0.8365742534076732,
      "gap": 12,
      "lastSeenTerm": "115000125"
    },
    {
      "combo": [
        19,
        31
      ],
      "count": 16,
      "weightedScore": 0.8338215711427618,
      "gap": 7,
      "lastSeenTerm": "115000130"
    },
    {
      "combo": [
        1,
        6
      ],
      "count": 15,
      "weightedScore": 0.8312250907183993,
      "gap": 25,
      "lastSeenTerm": "115000112"
    },
    {
      "combo": [
        11,
        37
      ],
      "count": 21,
      "weightedScore": 0.8263905980056887,
      "gap": 9,
      "lastSeenTerm": "115000128"
    },
    {
      "combo": [
        2,
        9
      ],
      "count": 17,
      "weightedScore": 0.8165449127555984,
      "gap": 20,
      "lastSeenTerm": "115000117"
    },
    {
      "combo": [
        1,
        13
      ],
      "count": 20,
      "weightedScore": 0.816158760369869,
      "gap": 18,
      "lastSeenTerm": "115000119"
    },
    {
      "combo": [
        11,
        33
      ],
      "count": 13,
      "weightedScore": 0.8119545284301937,
      "gap": 17,
      "lastSeenTerm": "115000120"
    },
    {
      "combo": [
        9,
        12
      ],
      "count": 18,
      "weightedScore": 0.8113897454755697,
      "gap": 7,
      "lastSeenTerm": "115000130"
    },
    {
      "combo": [
        12,
        19
      ],
      "count": 6,
      "weightedScore": 0.8112490164500893,
      "gap": 7,
      "lastSeenTerm": "115000130"
    },
    {
      "combo": [
        9,
        19
      ],
      "count": 12,
      "weightedScore": 0.8108372522354023,
      "gap": 7,
      "lastSeenTerm": "115000130"
    },
    {
      "combo": [
        3,
        19
      ],
      "count": 15,
      "weightedScore": 0.8069400285416509,
      "gap": 8,
      "lastSeenTerm": "115000129"
    },
    {
      "combo": [
        3,
        18
      ],
      "count": 12,
      "weightedScore": 0.8062064984723082,
      "gap": 8,
      "lastSeenTerm": "115000129"
    },
    {
      "combo": [
        23,
        25
      ],
      "count": 13,
      "weightedScore": 0.8040581664174694,
      "gap": 18,
      "lastSeenTerm": "115000119"
    },
    {
      "combo": [
        26,
        28
      ],
      "count": 17,
      "weightedScore": 0.8031963449515377,
      "gap": 24,
      "lastSeenTerm": "115000113"
    },
    {
      "combo": [
        7,
        37
      ],
      "count": 11,
      "weightedScore": 0.7976044235840145,
      "gap": 9,
      "lastSeenTerm": "115000128"
    },
    {
      "combo": [
        4,
        16
      ],
      "count": 18,
      "weightedScore": 0.7953740623510959,
      "gap": 12,
      "lastSeenTerm": "115000125"
    },
    {
      "combo": [
        15,
        33
      ],
      "count": 10,
      "weightedScore": 0.7943819717421232,
      "gap": 16,
      "lastSeenTerm": "115000121"
    },
    {
      "combo": [
        20,
        32
      ],
      "count": 14,
      "weightedScore": 0.7855071668353907,
      "gap": 16,
      "lastSeenTerm": "115000121"
    },
    {
      "combo": [
        12,
        37
      ],
      "count": 13,
      "weightedScore": 0.7850663433597164,
      "gap": 10,
      "lastSeenTerm": "115000127"
    },
    {
      "combo": [
        2,
        18
      ],
      "count": 10,
      "weightedScore": 0.7840383628224535,
      "gap": 8,
      "lastSeenTerm": "115000129"
    },
    {
      "combo": [
        7,
        38
      ],
      "count": 23,
      "weightedScore": 0.7828131662825344,
      "gap": 33,
      "lastSeenTerm": "115000104"
    },
    {
      "combo": [
        31,
        32
      ],
      "count": 14,
      "weightedScore": 0.7822334543852874,
      "gap": 15,
      "lastSeenTerm": "115000122"
    },
    {
      "combo": [
        11,
        22
      ],
      "count": 17,
      "weightedScore": 0.778440810579959,
      "gap": 23,
      "lastSeenTerm": "115000114"
    },
    {
      "combo": [
        34,
        36
      ],
      "count": 18,
      "weightedScore": 0.7726495033052572,
      "gap": 13,
      "lastSeenTerm": "115000124"
    },
    {
      "combo": [
        13,
        23
      ],
      "count": 17,
      "weightedScore": 0.7663616983358347,
      "gap": 18,
      "lastSeenTerm": "115000119"
    },
    {
      "combo": [
        11,
        34
      ],
      "count": 20,
      "weightedScore": 0.7620089783433035,
      "gap": 26,
      "lastSeenTerm": "115000111"
    },
    {
      "combo": [
        25,
        31
      ],
      "count": 15,
      "weightedScore": 0.7580348744333951,
      "gap": 41,
      "lastSeenTerm": "115000096"
    },
    {
      "combo": [
        6,
        38
      ],
      "count": 19,
      "weightedScore": 0.7535870315013968,
      "gap": 11,
      "lastSeenTerm": "115000126"
    },
    {
      "combo": [
        10,
        11
      ],
      "count": 14,
      "weightedScore": 0.7511211981422496,
      "gap": 26,
      "lastSeenTerm": "115000111"
    },
    {
      "combo": [
        22,
        32
      ],
      "count": 13,
      "weightedScore": 0.7454948940849031,
      "gap": 32,
      "lastSeenTerm": "115000105"
    },
    {
      "combo": [
        24,
        32
      ],
      "count": 13,
      "weightedScore": 0.7385140051156207,
      "gap": 15,
      "lastSeenTerm": "115000122"
    },
    {
      "combo": [
        1,
        20
      ],
      "count": 12,
      "weightedScore": 0.7384483200326589,
      "gap": 14,
      "lastSeenTerm": "115000123"
    },
    {
      "combo": [
        35,
        39
      ],
      "count": 14,
      "weightedScore": 0.7380664946131283,
      "gap": 19,
      "lastSeenTerm": "115000118"
    },
    {
      "combo": [
        1,
        35
      ],
      "count": 15,
      "weightedScore": 0.7343889565292195,
      "gap": 14,
      "lastSeenTerm": "115000123"
    },
    {
      "combo": [
        28,
        34
      ],
      "count": 10,
      "weightedScore": 0.7298962991060263,
      "gap": 13,
      "lastSeenTerm": "115000124"
    },
    {
      "combo": [
        16,
        38
      ],
      "count": 10,
      "weightedScore": 0.7273198902828012,
      "gap": 11,
      "lastSeenTerm": "115000126"
    },
    {
      "combo": [
        6,
        8
      ],
      "count": 17,
      "weightedScore": 0.7256051148930391,
      "gap": 43,
      "lastSeenTerm": "115000094"
    },
    {
      "combo": [
        4,
        15
      ],
      "count": 12,
      "weightedScore": 0.7223113091284397,
      "gap": 12,
      "lastSeenTerm": "115000125"
    },
    {
      "combo": [
        18,
        35
      ],
      "count": 15,
      "weightedScore": 0.7220222674220744,
      "gap": 19,
      "lastSeenTerm": "115000118"
    },
    {
      "combo": [
        9,
        23
      ],
      "count": 10,
      "weightedScore": 0.7199902384907302,
      "gap": 20,
      "lastSeenTerm": "115000117"
    },
    {
      "combo": [
        6,
        30
      ],
      "count": 9,
      "weightedScore": 0.7164701966413927,
      "gap": 31,
      "lastSeenTerm": "115000106"
    },
    {
      "combo": [
        15,
        24
      ],
      "count": 14,
      "weightedScore": 0.7162435201336803,
      "gap": 11,
      "lastSeenTerm": "115000126"
    },
    {
      "combo": [
        15,
        32
      ],
      "count": 9,
      "weightedScore": 0.7133018820475547,
      "gap": 16,
      "lastSeenTerm": "115000121"
    },
    {
      "combo": [
        2,
        16
      ],
      "count": 16,
      "weightedScore": 0.7094190322328676,
      "gap": 30,
      "lastSeenTerm": "115000107"
    },
    {
      "combo": [
        4,
        12
      ],
      "count": 15,
      "weightedScore": 0.7079372003927344,
      "gap": 21,
      "lastSeenTerm": "115000116"
    },
    {
      "combo": [
        7,
        24
      ],
      "count": 17,
      "weightedScore": 0.6999958097557151,
      "gap": 38,
      "lastSeenTerm": "115000099"
    },
    {
      "combo": [
        13,
        21
      ],
      "count": 10,
      "weightedScore": 0.6993722962382609,
      "gap": 22,
      "lastSeenTerm": "115000115"
    },
    {
      "combo": [
        11,
        32
      ],
      "count": 13,
      "weightedScore": 0.6981380593852449,
      "gap": 17,
      "lastSeenTerm": "115000120"
    },
    {
      "combo": [
        4,
        37
      ],
      "count": 17,
      "weightedScore": 0.6962989267738809,
      "gap": 12,
      "lastSeenTerm": "115000125"
    },
    {
      "combo": [
        15,
        31
      ],
      "count": 11,
      "weightedScore": 0.6947189665751127,
      "gap": 31,
      "lastSeenTerm": "115000106"
    },
    {
      "combo": [
        9,
        36
      ],
      "count": 16,
      "weightedScore": 0.6901618863627017,
      "gap": 13,
      "lastSeenTerm": "115000124"
    },
    {
      "combo": [
        1,
        12
      ],
      "count": 16,
      "weightedScore": 0.6884235599071394,
      "gap": 21,
      "lastSeenTerm": "115000116"
    },
    {
      "combo": [
        8,
        22
      ],
      "count": 19,
      "weightedScore": 0.6873706280376659,
      "gap": 28,
      "lastSeenTerm": "115000109"
    },
    {
      "combo": [
        25,
        28
      ],
      "count": 10,
      "weightedScore": 0.6873266347082168,
      "gap": 13,
      "lastSeenTerm": "115000124"
    },
    {
      "combo": [
        9,
        34
      ],
      "count": 13,
      "weightedScore": 0.679705423428729,
      "gap": 13,
      "lastSeenTerm": "115000124"
    },
    {
      "combo": [
        8,
        33
      ],
      "count": 8,
      "weightedScore": 0.6782504926234245,
      "gap": 16,
      "lastSeenTerm": "115000121"
    },
    {
      "combo": [
        9,
        28
      ],
      "count": 11,
      "weightedScore": 0.6739934232297556,
      "gap": 13,
      "lastSeenTerm": "115000124"
    },
    {
      "combo": [
        17,
        31
      ],
      "count": 13,
      "weightedScore": 0.6705726836313411,
      "gap": 47,
      "lastSeenTerm": "115000090"
    },
    {
      "combo": [
        6,
        25
      ],
      "count": 10,
      "weightedScore": 0.6692288811969709,
      "gap": 25,
      "lastSeenTerm": "115000112"
    },
    {
      "combo": [
        21,
        29
      ],
      "count": 12,
      "weightedScore": 0.6667268709312688,
      "gap": 36,
      "lastSeenTerm": "115000101"
    },
    {
      "combo": [
        1,
        18
      ],
      "count": 18,
      "weightedScore": 0.6547224275218004,
      "gap": 25,
      "lastSeenTerm": "115000112"
    },
    {
      "combo": [
        21,
        23
      ],
      "count": 17,
      "weightedScore": 0.6544402484884821,
      "gap": 14,
      "lastSeenTerm": "115000123"
    },
    {
      "combo": [
        7,
        23
      ],
      "count": 9,
      "weightedScore": 0.6528427580291005,
      "gap": 20,
      "lastSeenTerm": "115000117"
    },
    {
      "combo": [
        23,
        36
      ],
      "count": 17,
      "weightedScore": 0.6512400894158683,
      "gap": 18,
      "lastSeenTerm": "115000119"
    },
    {
      "combo": [
        8,
        9
      ],
      "count": 13,
      "weightedScore": 0.6500797314505404,
      "gap": 29,
      "lastSeenTerm": "115000108"
    },
    {
      "combo": [
        2,
        33
      ],
      "count": 14,
      "weightedScore": 0.6476015612721342,
      "gap": 17,
      "lastSeenTerm": "115000120"
    },
    {
      "combo": [
        28,
        35
      ],
      "count": 12,
      "weightedScore": 0.6468544313371529,
      "gap": 19,
      "lastSeenTerm": "115000118"
    },
    {
      "combo": [
        28,
        33
      ],
      "count": 10,
      "weightedScore": 0.646767251125183,
      "gap": 17,
      "lastSeenTerm": "115000120"
    },
    {
      "combo": [
        7,
        35
      ],
      "count": 20,
      "weightedScore": 0.6463983320464699,
      "gap": 33,
      "lastSeenTerm": "115000104"
    },
    {
      "combo": [
        4,
        32
      ],
      "count": 13,
      "weightedScore": 0.6443577027957194,
      "gap": 15,
      "lastSeenTerm": "115000122"
    },
    {
      "combo": [
        27,
        30
      ],
      "count": 19,
      "weightedScore": 0.643462152430806,
      "gap": 31,
      "lastSeenTerm": "115000106"
    },
    {
      "combo": [
        13,
        25
      ],
      "count": 11,
      "weightedScore": 0.6424558323751852,
      "gap": 18,
      "lastSeenTerm": "115000119"
    },
    {
      "combo": [
        4,
        24
      ],
      "count": 13,
      "weightedScore": 0.6424142592074285,
      "gap": 15,
      "lastSeenTerm": "115000122"
    },
    {
      "combo": [
        11,
        28
      ],
      "count": 10,
      "weightedScore": 0.6361679963742238,
      "gap": 17,
      "lastSeenTerm": "115000120"
    },
    {
      "combo": [
        30,
        31
      ],
      "count": 10,
      "weightedScore": 0.6353782871099035,
      "gap": 31,
      "lastSeenTerm": "115000106"
    },
    {
      "combo": [
        4,
        5
      ],
      "count": 16,
      "weightedScore": 0.6310872312296929,
      "gap": 40,
      "lastSeenTerm": "115000097"
    },
    {
      "combo": [
        3,
        33
      ],
      "count": 12,
      "weightedScore": 0.6297687547071971,
      "gap": 35,
      "lastSeenTerm": "115000102"
    },
    {
      "combo": [
        25,
        29
      ],
      "count": 12,
      "weightedScore": 0.6284996346910026,
      "gap": 36,
      "lastSeenTerm": "115000101"
    },
    {
      "combo": [
        24,
        37
      ],
      "count": 16,
      "weightedScore": 0.6280640590085564,
      "gap": 27,
      "lastSeenTerm": "115000110"
    },
    {
      "combo": [
        1,
        22
      ],
      "count": 15,
      "weightedScore": 0.6271124037391391,
      "gap": 21,
      "lastSeenTerm": "115000116"
    },
    {
      "combo": [
        1,
        4
      ],
      "count": 12,
      "weightedScore": 0.6219178281592285,
      "gap": 21,
      "lastSeenTerm": "115000116"
    },
    {
      "combo": [
        4,
        26
      ],
      "count": 13,
      "weightedScore": 0.6186444228013299,
      "gap": 21,
      "lastSeenTerm": "115000116"
    },
    {
      "combo": [
        18,
        36
      ],
      "count": 16,
      "weightedScore": 0.6138395145856324,
      "gap": 25,
      "lastSeenTerm": "115000112"
    },
    {
      "combo": [
        18,
        39
      ],
      "count": 16,
      "weightedScore": 0.6099317166339321,
      "gap": 19,
      "lastSeenTerm": "115000118"
    },
    {
      "combo": [
        8,
        28
      ],
      "count": 14,
      "weightedScore": 0.6096269137657647,
      "gap": 19,
      "lastSeenTerm": "115000118"
    },
    {
      "combo": [
        28,
        32
      ],
      "count": 9,
      "weightedScore": 0.6013117912497216,
      "gap": 17,
      "lastSeenTerm": "115000120"
    },
    {
      "combo": [
        11,
        18
      ],
      "count": 20,
      "weightedScore": 0.597740807852745,
      "gap": 23,
      "lastSeenTerm": "115000114"
    },
    {
      "combo": [
        2,
        28
      ],
      "count": 10,
      "weightedScore": 0.597170013791289,
      "gap": 17,
      "lastSeenTerm": "115000120"
    },
    {
      "combo": [
        4,
        36
      ],
      "count": 11,
      "weightedScore": 0.5961087479040734,
      "gap": 40,
      "lastSeenTerm": "115000097"
    },
    {
      "combo": [
        4,
        22
      ],
      "count": 17,
      "weightedScore": 0.5958547423699649,
      "gap": 21,
      "lastSeenTerm": "115000116"
    },
    {
      "combo": [
        11,
        39
      ],
      "count": 9,
      "weightedScore": 0.5905174750575947,
      "gap": 26,
      "lastSeenTerm": "115000111"
    },
    {
      "combo": [
        3,
        36
      ],
      "count": 19,
      "weightedScore": 0.5889364157839718,
      "gap": 40,
      "lastSeenTerm": "115000097"
    },
    {
      "combo": [
        29,
        34
      ],
      "count": 19,
      "weightedScore": 0.5865401769845391,
      "gap": 36,
      "lastSeenTerm": "115000101"
    },
    {
      "combo": [
        6,
        7
      ],
      "count": 21,
      "weightedScore": 0.5863865962613939,
      "gap": 20,
      "lastSeenTerm": "115000117"
    },
    {
      "combo": [
        10,
        34
      ],
      "count": 9,
      "weightedScore": 0.5854388157154747,
      "gap": 26,
      "lastSeenTerm": "115000111"
    },
    {
      "combo": [
        6,
        23
      ],
      "count": 11,
      "weightedScore": 0.5849257439393835,
      "gap": 20,
      "lastSeenTerm": "115000117"
    },
    {
      "combo": [
        11,
        21
      ],
      "count": 14,
      "weightedScore": 0.5828290521824833,
      "gap": 23,
      "lastSeenTerm": "115000114"
    },
    {
      "combo": [
        9,
        17
      ],
      "count": 11,
      "weightedScore": 0.5795894267076055,
      "gap": 29,
      "lastSeenTerm": "115000108"
    },
    {
      "combo": [
        28,
        39
      ],
      "count": 16,
      "weightedScore": 0.5746727246264339,
      "gap": 19,
      "lastSeenTerm": "115000118"
    },
    {
      "combo": [
        18,
        22
      ],
      "count": 13,
      "weightedScore": 0.5724488543679486,
      "gap": 23,
      "lastSeenTerm": "115000114"
    },
    {
      "combo": [
        21,
        37
      ],
      "count": 15,
      "weightedScore": 0.5635195413622744,
      "gap": 22,
      "lastSeenTerm": "115000115"
    },
    {
      "combo": [
        25,
        35
      ],
      "count": 15,
      "weightedScore": 0.5615899499327918,
      "gap": 37,
      "lastSeenTerm": "115000100"
    },
    {
      "combo": [
        6,
        22
      ],
      "count": 14,
      "weightedScore": 0.5588909996387704,
      "gap": 32,
      "lastSeenTerm": "115000105"
    },
    {
      "combo": [
        7,
        9
      ],
      "count": 13,
      "weightedScore": 0.5505295622004396,
      "gap": 20,
      "lastSeenTerm": "115000117"
    },
    {
      "combo": [
        2,
        23
      ],
      "count": 10,
      "weightedScore": 0.543879337091347,
      "gap": 20,
      "lastSeenTerm": "115000117"
    },
    {
      "combo": [
        13,
        37
      ],
      "count": 20,
      "weightedScore": 0.5386182313536525,
      "gap": 22,
      "lastSeenTerm": "115000115"
    },
    {
      "combo": [
        16,
        25
      ],
      "count": 11,
      "weightedScore": 0.5363061527095706,
      "gap": 36,
      "lastSeenTerm": "115000101"
    },
    {
      "combo": [
        31,
        38
      ],
      "count": 14,
      "weightedScore": 0.5340986696635981,
      "gap": 46,
      "lastSeenTerm": "115000091"
    },
    {
      "combo": [
        4,
        11
      ],
      "count": 17,
      "weightedScore": 0.5255328971067615,
      "gap": 26,
      "lastSeenTerm": "115000111"
    },
    {
      "combo": [
        8,
        36
      ],
      "count": 17,
      "weightedScore": 0.5253291434848435,
      "gap": 28,
      "lastSeenTerm": "115000109"
    },
    {
      "combo": [
        21,
        30
      ],
      "count": 11,
      "weightedScore": 0.5234579527230581,
      "gap": 43,
      "lastSeenTerm": "115000094"
    },
    {
      "combo": [
        11,
        25
      ],
      "count": 16,
      "weightedScore": 0.520114985400007,
      "gap": 23,
      "lastSeenTerm": "115000114"
    },
    {
      "combo": [
        11,
        17
      ],
      "count": 16,
      "weightedScore": 0.5178206049783128,
      "gap": 52,
      "lastSeenTerm": "115000085"
    },
    {
      "combo": [
        9,
        29
      ],
      "count": 16,
      "weightedScore": 0.5175224888303125,
      "gap": 44,
      "lastSeenTerm": "115000093"
    },
    {
      "combo": [
        20,
        22
      ],
      "count": 12,
      "weightedScore": 0.5152659013672034,
      "gap": 35,
      "lastSeenTerm": "115000102"
    },
    {
      "combo": [
        23,
        26
      ],
      "count": 17,
      "weightedScore": 0.5137335420489632,
      "gap": 24,
      "lastSeenTerm": "115000113"
    },
    {
      "combo": [
        9,
        30
      ],
      "count": 16,
      "weightedScore": 0.5128078433117693,
      "gap": 44,
      "lastSeenTerm": "115000093"
    },
    {
      "combo": [
        21,
        36
      ],
      "count": 12,
      "weightedScore": 0.5116819049723799,
      "gap": 22,
      "lastSeenTerm": "115000115"
    },
    {
      "combo": [
        8,
        12
      ],
      "count": 15,
      "weightedScore": 0.5080254942696518,
      "gap": 43,
      "lastSeenTerm": "115000094"
    },
    {
      "combo": [
        19,
        23
      ],
      "count": 11,
      "weightedScore": 0.5072991556087668,
      "gap": 24,
      "lastSeenTerm": "115000113"
    },
    {
      "combo": [
        4,
        34
      ],
      "count": 18,
      "weightedScore": 0.5068029469264113,
      "gap": 26,
      "lastSeenTerm": "115000111"
    },
    {
      "combo": [
        22,
        25
      ],
      "count": 10,
      "weightedScore": 0.5029967599917335,
      "gap": 23,
      "lastSeenTerm": "115000114"
    },
    {
      "combo": [
        22,
        39
      ],
      "count": 11,
      "weightedScore": 0.5026862441847473,
      "gap": 28,
      "lastSeenTerm": "115000109"
    },
    {
      "combo": [
        27,
        29
      ],
      "count": 16,
      "weightedScore": 0.5005005610552034,
      "gap": 45,
      "lastSeenTerm": "115000092"
    },
    {
      "combo": [
        18,
        34
      ],
      "count": 12,
      "weightedScore": 0.49516464356694245,
      "gap": 60,
      "lastSeenTerm": "115000077"
    },
    {
      "combo": [
        23,
        28
      ],
      "count": 9,
      "weightedScore": 0.48979617558875954,
      "gap": 24,
      "lastSeenTerm": "115000113"
    },
    {
      "combo": [
        5,
        7
      ],
      "count": 15,
      "weightedScore": 0.48838547893034734,
      "gap": 38,
      "lastSeenTerm": "115000099"
    },
    {
      "combo": [
        9,
        27
      ],
      "count": 19,
      "weightedScore": 0.48656745441060945,
      "gap": 45,
      "lastSeenTerm": "115000092"
    },
    {
      "combo": [
        18,
        26
      ],
      "count": 15,
      "weightedScore": 0.48585646303973107,
      "gap": 24,
      "lastSeenTerm": "115000113"
    },
    {
      "combo": [
        19,
        26
      ],
      "count": 15,
      "weightedScore": 0.48164397795208247,
      "gap": 24,
      "lastSeenTerm": "115000113"
    },
    {
      "combo": [
        15,
        27
      ],
      "count": 12,
      "weightedScore": 0.4806297635646736,
      "gap": 31,
      "lastSeenTerm": "115000106"
    },
    {
      "combo": [
        18,
        20
      ],
      "count": 15,
      "weightedScore": 0.47739963600179014,
      "gap": 34,
      "lastSeenTerm": "115000103"
    },
    {
      "combo": [
        34,
        39
      ],
      "count": 11,
      "weightedScore": 0.4745312569041255,
      "gap": 26,
      "lastSeenTerm": "115000111"
    },
    {
      "combo": [
        10,
        39
      ],
      "count": 13,
      "weightedScore": 0.47341449156988863,
      "gap": 26,
      "lastSeenTerm": "115000111"
    },
    {
      "combo": [
        6,
        18
      ],
      "count": 11,
      "weightedScore": 0.4683457025434313,
      "gap": 25,
      "lastSeenTerm": "115000112"
    },
    {
      "combo": [
        24,
        27
      ],
      "count": 20,
      "weightedScore": 0.46738277647344484,
      "gap": 27,
      "lastSeenTerm": "115000110"
    },
    {
      "combo": [
        36,
        39
      ],
      "count": 20,
      "weightedScore": 0.4666335677105598,
      "gap": 28,
      "lastSeenTerm": "115000109"
    },
    {
      "combo": [
        23,
        27
      ],
      "count": 17,
      "weightedScore": 0.46444195264689747,
      "gap": 34,
      "lastSeenTerm": "115000103"
    },
    {
      "combo": [
        12,
        21
      ],
      "count": 15,
      "weightedScore": 0.4633238230071962,
      "gap": 43,
      "lastSeenTerm": "115000094"
    },
    {
      "combo": [
        32,
        36
      ],
      "count": 12,
      "weightedScore": 0.4607466902375844,
      "gap": 32,
      "lastSeenTerm": "115000105"
    },
    {
      "combo": [
        20,
        36
      ],
      "count": 16,
      "weightedScore": 0.46063353763555503,
      "gap": 40,
      "lastSeenTerm": "115000097"
    },
    {
      "combo": [
        21,
        34
      ],
      "count": 15,
      "weightedScore": 0.45772036139219846,
      "gap": 36,
      "lastSeenTerm": "115000101"
    },
    {
      "combo": [
        4,
        10
      ],
      "count": 15,
      "weightedScore": 0.45479899003028623,
      "gap": 26,
      "lastSeenTerm": "115000111"
    },
    {
      "combo": [
        16,
        27
      ],
      "count": 11,
      "weightedScore": 0.4513261335496613,
      "gap": 27,
      "lastSeenTerm": "115000110"
    },
    {
      "combo": [
        20,
        27
      ],
      "count": 10,
      "weightedScore": 0.4510437050073495,
      "gap": 34,
      "lastSeenTerm": "115000103"
    },
    {
      "combo": [
        27,
        37
      ],
      "count": 20,
      "weightedScore": 0.44895726415768245,
      "gap": 27,
      "lastSeenTerm": "115000110"
    },
    {
      "combo": [
        7,
        17
      ],
      "count": 11,
      "weightedScore": 0.44815026521855994,
      "gap": 47,
      "lastSeenTerm": "115000090"
    },
    {
      "combo": [
        8,
        26
      ],
      "count": 13,
      "weightedScore": 0.44636593933687463,
      "gap": 28,
      "lastSeenTerm": "115000109"
    },
    {
      "combo": [
        7,
        29
      ],
      "count": 16,
      "weightedScore": 0.43892787982704756,
      "gap": 41,
      "lastSeenTerm": "115000096"
    },
    {
      "combo": [
        5,
        38
      ],
      "count": 17,
      "weightedScore": 0.4369313760001874,
      "gap": 38,
      "lastSeenTerm": "115000099"
    },
    {
      "combo": [
        4,
        29
      ],
      "count": 17,
      "weightedScore": 0.43647723898413726,
      "gap": 50,
      "lastSeenTerm": "115000087"
    },
    {
      "combo": [
        9,
        38
      ],
      "count": 16,
      "weightedScore": 0.43199834831045664,
      "gap": 29,
      "lastSeenTerm": "115000108"
    },
    {
      "combo": [
        15,
        30
      ],
      "count": 12,
      "weightedScore": 0.4317646341319742,
      "gap": 31,
      "lastSeenTerm": "115000106"
    },
    {
      "combo": [
        26,
        39
      ],
      "count": 13,
      "weightedScore": 0.43106000248238197,
      "gap": 28,
      "lastSeenTerm": "115000109"
    },
    {
      "combo": [
        26,
        36
      ],
      "count": 10,
      "weightedScore": 0.4301347312563958,
      "gap": 28,
      "lastSeenTerm": "115000109"
    },
    {
      "combo": [
        9,
        21
      ],
      "count": 12,
      "weightedScore": 0.4299612330062086,
      "gap": 48,
      "lastSeenTerm": "115000089"
    },
    {
      "combo": [
        9,
        35
      ],
      "count": 14,
      "weightedScore": 0.42872775725957313,
      "gap": 54,
      "lastSeenTerm": "115000083"
    },
    {
      "combo": [
        12,
        17
      ],
      "count": 11,
      "weightedScore": 0.42862306894778646,
      "gap": 47,
      "lastSeenTerm": "115000090"
    },
    {
      "combo": [
        9,
        11
      ],
      "count": 10,
      "weightedScore": 0.42759202843278704,
      "gap": 44,
      "lastSeenTerm": "115000093"
    },
    {
      "combo": [
        2,
        15
      ],
      "count": 14,
      "weightedScore": 0.4226448887043194,
      "gap": 49,
      "lastSeenTerm": "115000088"
    },
    {
      "combo": [
        16,
        29
      ],
      "count": 20,
      "weightedScore": 0.42231390696402304,
      "gap": 36,
      "lastSeenTerm": "115000101"
    },
    {
      "combo": [
        12,
        24
      ],
      "count": 19,
      "weightedScore": 0.4214776814432156,
      "gap": 47,
      "lastSeenTerm": "115000090"
    },
    {
      "combo": [
        17,
        34
      ],
      "count": 9,
      "weightedScore": 0.41986200544982283,
      "gap": 52,
      "lastSeenTerm": "115000085"
    },
    {
      "combo": [
        3,
        11
      ],
      "count": 21,
      "weightedScore": 0.41785592677215266,
      "gap": 56,
      "lastSeenTerm": "115000081"
    },
    {
      "combo": [
        3,
        14
      ],
      "count": 10,
      "weightedScore": 0.4155158661206788,
      "gap": 30,
      "lastSeenTerm": "115000107"
    },
    {
      "combo": [
        16,
        21
      ],
      "count": 15,
      "weightedScore": 0.4142677110084436,
      "gap": 36,
      "lastSeenTerm": "115000101"
    },
    {
      "combo": [
        3,
        16
      ],
      "count": 8,
      "weightedScore": 0.40890910935321195,
      "gap": 30,
      "lastSeenTerm": "115000107"
    },
    {
      "combo": [
        2,
        20
      ],
      "count": 9,
      "weightedScore": 0.4079907952594603,
      "gap": 30,
      "lastSeenTerm": "115000107"
    },
    {
      "combo": [
        31,
        36
      ],
      "count": 13,
      "weightedScore": 0.40784580249091756,
      "gap": 53,
      "lastSeenTerm": "115000084"
    },
    {
      "combo": [
        16,
        20
      ],
      "count": 12,
      "weightedScore": 0.40267470692384,
      "gap": 30,
      "lastSeenTerm": "115000107"
    },
    {
      "combo": [
        14,
        16
      ],
      "count": 6,
      "weightedScore": 0.40183486453747774,
      "gap": 30,
      "lastSeenTerm": "115000107"
    },
    {
      "combo": [
        37,
        38
      ],
      "count": 18,
      "weightedScore": 0.40027970885155834,
      "gap": 46,
      "lastSeenTerm": "115000091"
    },
    {
      "combo": [
        17,
        24
      ],
      "count": 16,
      "weightedScore": 0.39540007333001725,
      "gap": 47,
      "lastSeenTerm": "115000090"
    },
    {
      "combo": [
        6,
        27
      ],
      "count": 9,
      "weightedScore": 0.39232779892067504,
      "gap": 31,
      "lastSeenTerm": "115000106"
    },
    {
      "combo": [
        2,
        22
      ],
      "count": 11,
      "weightedScore": 0.39043975400583114,
      "gap": 32,
      "lastSeenTerm": "115000105"
    },
    {
      "combo": [
        17,
        36
      ],
      "count": 14,
      "weightedScore": 0.39025655821810945,
      "gap": 53,
      "lastSeenTerm": "115000084"
    },
    {
      "combo": [
        3,
        22
      ],
      "count": 12,
      "weightedScore": 0.38829985987366167,
      "gap": 35,
      "lastSeenTerm": "115000102"
    },
    {
      "combo": [
        30,
        37
      ],
      "count": 11,
      "weightedScore": 0.38502808544628764,
      "gap": 46,
      "lastSeenTerm": "115000091"
    },
    {
      "combo": [
        35,
        38
      ],
      "count": 16,
      "weightedScore": 0.3801385242819276,
      "gap": 33,
      "lastSeenTerm": "115000104"
    },
    {
      "combo": [
        16,
        34
      ],
      "count": 15,
      "weightedScore": 0.3798872973799464,
      "gap": 36,
      "lastSeenTerm": "115000101"
    },
    {
      "combo": [
        18,
        27
      ],
      "count": 12,
      "weightedScore": 0.3792253021839333,
      "gap": 34,
      "lastSeenTerm": "115000103"
    },
    {
      "combo": [
        7,
        8
      ],
      "count": 19,
      "weightedScore": 0.3786729982084004,
      "gap": 33,
      "lastSeenTerm": "115000104"
    },
    {
      "combo": [
        21,
        38
      ],
      "count": 17,
      "weightedScore": 0.3774184054836501,
      "gap": 33,
      "lastSeenTerm": "115000104"
    },
    {
      "combo": [
        4,
        27
      ],
      "count": 15,
      "weightedScore": 0.3769741002959496,
      "gap": 51,
      "lastSeenTerm": "115000086"
    },
    {
      "combo": [
        25,
        30
      ],
      "count": 11,
      "weightedScore": 0.37533302180362743,
      "gap": 48,
      "lastSeenTerm": "115000089"
    },
    {
      "combo": [
        10,
        17
      ],
      "count": 11,
      "weightedScore": 0.3742190407264364,
      "gap": 37,
      "lastSeenTerm": "115000100"
    },
    {
      "combo": [
        29,
        31
      ],
      "count": 8,
      "weightedScore": 0.37001923495862876,
      "gap": 41,
      "lastSeenTerm": "115000096"
    },
    {
      "combo": [
        10,
        35
      ],
      "count": 15,
      "weightedScore": 0.3651466319636454,
      "gap": 37,
      "lastSeenTerm": "115000100"
    },
    {
      "combo": [
        2,
        26
      ],
      "count": 8,
      "weightedScore": 0.36492046679495177,
      "gap": 42,
      "lastSeenTerm": "115000095"
    },
    {
      "combo": [
        11,
        13
      ],
      "count": 12,
      "weightedScore": 0.36103633228424653,
      "gap": 56,
      "lastSeenTerm": "115000081"
    },
    {
      "combo": [
        2,
        10
      ],
      "count": 15,
      "weightedScore": 0.35993810698654194,
      "gap": 37,
      "lastSeenTerm": "115000100"
    },
    {
      "combo": [
        8,
        23
      ],
      "count": 13,
      "weightedScore": 0.35667901397209095,
      "gap": 34,
      "lastSeenTerm": "115000103"
    },
    {
      "combo": [
        21,
        33
      ],
      "count": 11,
      "weightedScore": 0.34671147253828133,
      "gap": 35,
      "lastSeenTerm": "115000102"
    },
    {
      "combo": [
        6,
        26
      ],
      "count": 13,
      "weightedScore": 0.3455659551233782,
      "gap": 39,
      "lastSeenTerm": "115000098"
    },
    {
      "combo": [
        22,
        33
      ],
      "count": 5,
      "weightedScore": 0.34449664696304577,
      "gap": 35,
      "lastSeenTerm": "115000102"
    },
    {
      "combo": [
        2,
        5
      ],
      "count": 12,
      "weightedScore": 0.34330331073142856,
      "gap": 50,
      "lastSeenTerm": "115000087"
    },
    {
      "combo": [
        9,
        16
      ],
      "count": 8,
      "weightedScore": 0.3430421832950487,
      "gap": 57,
      "lastSeenTerm": "115000080"
    },
    {
      "combo": [
        1,
        2
      ],
      "count": 13,
      "weightedScore": 0.3412760772439216,
      "gap": 42,
      "lastSeenTerm": "115000095"
    },
    {
      "combo": [
        11,
        29
      ],
      "count": 20,
      "weightedScore": 0.3403186403851257,
      "gap": 44,
      "lastSeenTerm": "115000093"
    },
    {
      "combo": [
        6,
        28
      ],
      "count": 13,
      "weightedScore": 0.33904824970469327,
      "gap": 39,
      "lastSeenTerm": "115000098"
    },
    {
      "combo": [
        11,
        15
      ],
      "count": 19,
      "weightedScore": 0.3371504879168288,
      "gap": 66,
      "lastSeenTerm": "115000071"
    },
    {
      "combo": [
        3,
        5
      ],
      "count": 17,
      "weightedScore": 0.3366059486209289,
      "gap": 40,
      "lastSeenTerm": "115000097"
    },
    {
      "combo": [
        7,
        15
      ],
      "count": 12,
      "weightedScore": 0.33246190867843717,
      "gap": 65,
      "lastSeenTerm": "115000072"
    },
    {
      "combo": [
        17,
        35
      ],
      "count": 16,
      "weightedScore": 0.33180808975927156,
      "gap": 37,
      "lastSeenTerm": "115000100"
    },
    {
      "combo": [
        1,
        14
      ],
      "count": 16,
      "weightedScore": 0.32922047358295126,
      "gap": 39,
      "lastSeenTerm": "115000098"
    },
    {
      "combo": [
        7,
        39
      ],
      "count": 12,
      "weightedScore": 0.32852228026808783,
      "gap": 38,
      "lastSeenTerm": "115000099"
    },
    {
      "combo": [
        10,
        25
      ],
      "count": 8,
      "weightedScore": 0.3261519811557026,
      "gap": 37,
      "lastSeenTerm": "115000100"
    },
    {
      "combo": [
        5,
        15
      ],
      "count": 9,
      "weightedScore": 0.32604369016694723,
      "gap": 72,
      "lastSeenTerm": "115000065"
    },
    {
      "combo": [
        6,
        21
      ],
      "count": 12,
      "weightedScore": 0.32590983128699885,
      "gap": 43,
      "lastSeenTerm": "115000094"
    },
    {
      "combo": [
        38,
        39
      ],
      "count": 20,
      "weightedScore": 0.32295908336652596,
      "gap": 38,
      "lastSeenTerm": "115000099"
    },
    {
      "combo": [
        2,
        31
      ],
      "count": 10,
      "weightedScore": 0.3212519540278763,
      "gap": 49,
      "lastSeenTerm": "115000088"
    },
    {
      "combo": [
        1,
        28
      ],
      "count": 10,
      "weightedScore": 0.32096312409743843,
      "gap": 39,
      "lastSeenTerm": "115000098"
    },
    {
      "combo": [
        25,
        26
      ],
      "count": 10,
      "weightedScore": 0.32057179541842773,
      "gap": 41,
      "lastSeenTerm": "115000096"
    },
    {
      "combo": [
        5,
        39
      ],
      "count": 12,
      "weightedScore": 0.3196860427015618,
      "gap": 38,
      "lastSeenTerm": "115000099"
    },
    {
      "combo": [
        5,
        23
      ],
      "count": 17,
      "weightedScore": 0.31714737577508123,
      "gap": 67,
      "lastSeenTerm": "115000070"
    },
    {
      "combo": [
        5,
        24
      ],
      "count": 15,
      "weightedScore": 0.3171448086225909,
      "gap": 38,
      "lastSeenTerm": "115000099"
    },
    {
      "combo": [
        16,
        17
      ],
      "count": 11,
      "weightedScore": 0.31667246686692463,
      "gap": 59,
      "lastSeenTerm": "115000078"
    },
    {
      "combo": [
        24,
        39
      ],
      "count": 16,
      "weightedScore": 0.3151771959520985,
      "gap": 38,
      "lastSeenTerm": "115000099"
    },
    {
      "combo": [
        1,
        16
      ],
      "count": 14,
      "weightedScore": 0.3142717952141063,
      "gap": 42,
      "lastSeenTerm": "115000095"
    },
    {
      "combo": [
        3,
        31
      ],
      "count": 16,
      "weightedScore": 0.313196303169338,
      "gap": 62,
      "lastSeenTerm": "115000075"
    },
    {
      "combo": [
        11,
        23
      ],
      "count": 20,
      "weightedScore": 0.3121198280864497,
      "gap": 56,
      "lastSeenTerm": "115000081"
    },
    {
      "combo": [
        16,
        23
      ],
      "count": 18,
      "weightedScore": 0.3076083064919116,
      "gap": 57,
      "lastSeenTerm": "115000080"
    },
    {
      "combo": [
        22,
        27
      ],
      "count": 16,
      "weightedScore": 0.3068215507833138,
      "gap": 69,
      "lastSeenTerm": "115000068"
    },
    {
      "combo": [
        14,
        26
      ],
      "count": 16,
      "weightedScore": 0.30557018441769207,
      "gap": 39,
      "lastSeenTerm": "115000098"
    },
    {
      "combo": [
        4,
        20
      ],
      "count": 15,
      "weightedScore": 0.30521506833040235,
      "gap": 40,
      "lastSeenTerm": "115000097"
    },
    {
      "combo": [
        6,
        14
      ],
      "count": 16,
      "weightedScore": 0.30490442121058847,
      "gap": 39,
      "lastSeenTerm": "115000098"
    },
    {
      "combo": [
        8,
        30
      ],
      "count": 9,
      "weightedScore": 0.3044376612019944,
      "gap": 43,
      "lastSeenTerm": "115000094"
    },
    {
      "combo": [
        7,
        25
      ],
      "count": 13,
      "weightedScore": 0.302263281884815,
      "gap": 41,
      "lastSeenTerm": "115000096"
    },
    {
      "combo": [
        29,
        33
      ],
      "count": 6,
      "weightedScore": 0.3006790140500591,
      "gap": 45,
      "lastSeenTerm": "115000092"
    },
    {
      "combo": [
        6,
        11
      ],
      "count": 19,
      "weightedScore": 0.3001488801224077,
      "gap": 59,
      "lastSeenTerm": "115000078"
    },
    {
      "combo": [
        29,
        30
      ],
      "count": 9,
      "weightedScore": 0.2962462286561389,
      "gap": 44,
      "lastSeenTerm": "115000093"
    },
    {
      "combo": [
        31,
        37
      ],
      "count": 10,
      "weightedScore": 0.29332932887710794,
      "gap": 46,
      "lastSeenTerm": "115000091"
    },
    {
      "combo": [
        16,
        26
      ],
      "count": 16,
      "weightedScore": 0.293291631336854,
      "gap": 42,
      "lastSeenTerm": "115000095"
    },
    {
      "combo": [
        12,
        32
      ],
      "count": 11,
      "weightedScore": 0.29277514412070677,
      "gap": 75,
      "lastSeenTerm": "115000062"
    },
    {
      "combo": [
        4,
        17
      ],
      "count": 13,
      "weightedScore": 0.2923720540960786,
      "gap": 53,
      "lastSeenTerm": "115000084"
    },
    {
      "combo": [
        19,
        22
      ],
      "count": 15,
      "weightedScore": 0.2922157829486687,
      "gap": 65,
      "lastSeenTerm": "115000072"
    },
    {
      "combo": [
        7,
        16
      ],
      "count": 11,
      "weightedScore": 0.29211917191102355,
      "gap": 42,
      "lastSeenTerm": "115000095"
    },
    {
      "combo": [
        26,
        29
      ],
      "count": 10,
      "weightedScore": 0.29168627108078105,
      "gap": 41,
      "lastSeenTerm": "115000096"
    },
    {
      "combo": [
        25,
        27
      ],
      "count": 10,
      "weightedScore": 0.29114544496876466,
      "gap": 48,
      "lastSeenTerm": "115000089"
    },
    {
      "combo": [
        11,
        30
      ],
      "count": 17,
      "weightedScore": 0.28976227960244416,
      "gap": 44,
      "lastSeenTerm": "115000093"
    },
    {
      "combo": [
        1,
        7
      ],
      "count": 10,
      "weightedScore": 0.28937308577404725,
      "gap": 42,
      "lastSeenTerm": "115000095"
    },
    {
      "combo": [
        15,
        25
      ],
      "count": 11,
      "weightedScore": 0.28374221082079126,
      "gap": 49,
      "lastSeenTerm": "115000088"
    },
    {
      "combo": [
        8,
        34
      ],
      "count": 17,
      "weightedScore": 0.2798211315528149,
      "gap": 60,
      "lastSeenTerm": "115000077"
    },
    {
      "combo": [
        27,
        33
      ],
      "count": 19,
      "weightedScore": 0.27633587382881464,
      "gap": 45,
      "lastSeenTerm": "115000092"
    },
    {
      "combo": [
        10,
        20
      ],
      "count": 9,
      "weightedScore": 0.27591506316906733,
      "gap": 63,
      "lastSeenTerm": "115000074"
    },
    {
      "combo": [
        14,
        33
      ],
      "count": 18,
      "weightedScore": 0.27526815887085093,
      "gap": 45,
      "lastSeenTerm": "115000092"
    },
    {
      "combo": [
        2,
        30
      ],
      "count": 12,
      "weightedScore": 0.2748083370650569,
      "gap": 44,
      "lastSeenTerm": "115000093"
    },
    {
      "combo": [
        9,
        33
      ],
      "count": 17,
      "weightedScore": 0.2746258576681074,
      "gap": 45,
      "lastSeenTerm": "115000092"
    },
    {
      "combo": [
        10,
        36
      ],
      "count": 12,
      "weightedScore": 0.27310299999822674,
      "gap": 63,
      "lastSeenTerm": "115000074"
    },
    {
      "combo": [
        7,
        34
      ],
      "count": 19,
      "weightedScore": 0.27103592054730546,
      "gap": 52,
      "lastSeenTerm": "115000085"
    },
    {
      "combo": [
        18,
        30
      ],
      "count": 11,
      "weightedScore": 0.2694017195213428,
      "gap": 46,
      "lastSeenTerm": "115000091"
    },
    {
      "combo": [
        3,
        10
      ],
      "count": 15,
      "weightedScore": 0.2688774851256201,
      "gap": 56,
      "lastSeenTerm": "115000081"
    },
    {
      "combo": [
        9,
        14
      ],
      "count": 13,
      "weightedScore": 0.2667713455930171,
      "gap": 45,
      "lastSeenTerm": "115000092"
    },
    {
      "combo": [
        13,
        18
      ],
      "count": 16,
      "weightedScore": 0.2651602138799629,
      "gap": 55,
      "lastSeenTerm": "115000082"
    },
    {
      "combo": [
        14,
        17
      ],
      "count": 9,
      "weightedScore": 0.2619422737544818,
      "gap": 61,
      "lastSeenTerm": "115000076"
    },
    {
      "combo": [
        31,
        34
      ],
      "count": 11,
      "weightedScore": 0.2606025898452063,
      "gap": 52,
      "lastSeenTerm": "115000085"
    },
    {
      "combo": [
        6,
        29
      ],
      "count": 11,
      "weightedScore": 0.2594761352590186,
      "gap": 50,
      "lastSeenTerm": "115000087"
    },
    {
      "combo": [
        14,
        27
      ],
      "count": 17,
      "weightedScore": 0.25787907700799806,
      "gap": 45,
      "lastSeenTerm": "115000092"
    },
    {
      "combo": [
        24,
        34
      ],
      "count": 13,
      "weightedScore": 0.25786586312688137,
      "gap": 60,
      "lastSeenTerm": "115000077"
    },
    {
      "combo": [
        11,
        12
      ],
      "count": 15,
      "weightedScore": 0.25715425545738296,
      "gap": 72,
      "lastSeenTerm": "115000065"
    },
    {
      "combo": [
        9,
        39
      ],
      "count": 19,
      "weightedScore": 0.2569621060405941,
      "gap": 57,
      "lastSeenTerm": "115000080"
    },
    {
      "combo": [
        30,
        38
      ],
      "count": 16,
      "weightedScore": 0.2554165577191336,
      "gap": 46,
      "lastSeenTerm": "115000091"
    },
    {
      "combo": [
        14,
        29
      ],
      "count": 11,
      "weightedScore": 0.25429780908861166,
      "gap": 45,
      "lastSeenTerm": "115000092"
    },
    {
      "combo": [
        32,
        35
      ],
      "count": 13,
      "weightedScore": 0.2536749402465284,
      "gap": 68,
      "lastSeenTerm": "115000069"
    },
    {
      "combo": [
        16,
        35
      ],
      "count": 8,
      "weightedScore": 0.25351196645384616,
      "gap": 57,
      "lastSeenTerm": "115000080"
    },
    {
      "combo": [
        23,
        39
      ],
      "count": 10,
      "weightedScore": 0.2527279841898186,
      "gap": 57,
      "lastSeenTerm": "115000080"
    },
    {
      "combo": [
        18,
        31
      ],
      "count": 12,
      "weightedScore": 0.2508321240549445,
      "gap": 46,
      "lastSeenTerm": "115000091"
    },
    {
      "combo": [
        21,
        32
      ],
      "count": 11,
      "weightedScore": 0.24865892282718777,
      "gap": 68,
      "lastSeenTerm": "115000069"
    },
    {
      "combo": [
        18,
        37
      ],
      "count": 16,
      "weightedScore": 0.2486376950003948,
      "gap": 46,
      "lastSeenTerm": "115000091"
    },
    {
      "combo": [
        18,
        38
      ],
      "count": 6,
      "weightedScore": 0.24635798287142946,
      "gap": 46,
      "lastSeenTerm": "115000091"
    },
    {
      "combo": [
        19,
        34
      ],
      "count": 10,
      "weightedScore": 0.2434576038342503,
      "gap": 70,
      "lastSeenTerm": "115000067"
    },
    {
      "combo": [
        5,
        29
      ],
      "count": 12,
      "weightedScore": 0.24035026844263635,
      "gap": 50,
      "lastSeenTerm": "115000087"
    },
    {
      "combo": [
        11,
        31
      ],
      "count": 15,
      "weightedScore": 0.23985712303055468,
      "gap": 52,
      "lastSeenTerm": "115000085"
    },
    {
      "combo": [
        19,
        29
      ],
      "count": 11,
      "weightedScore": 0.2351264952045942,
      "gap": 70,
      "lastSeenTerm": "115000067"
    },
    {
      "combo": [
        6,
        20
      ],
      "count": 15,
      "weightedScore": 0.22747394306818097,
      "gap": 58,
      "lastSeenTerm": "115000079"
    },
    {
      "combo": [
        9,
        13
      ],
      "count": 7,
      "weightedScore": 0.22692527384221278,
      "gap": 55,
      "lastSeenTerm": "115000082"
    },
    {
      "combo": [
        6,
        35
      ],
      "count": 12,
      "weightedScore": 0.22276197687899066,
      "gap": 54,
      "lastSeenTerm": "115000083"
    },
    {
      "combo": [
        3,
        23
      ],
      "count": 13,
      "weightedScore": 0.21924328045083671,
      "gap": 56,
      "lastSeenTerm": "115000081"
    },
    {
      "combo": [
        4,
        21
      ],
      "count": 9,
      "weightedScore": 0.21647804549563776,
      "gap": 51,
      "lastSeenTerm": "115000086"
    },
    {
      "combo": [
        10,
        23
      ],
      "count": 12,
      "weightedScore": 0.21440829950721266,
      "gap": 56,
      "lastSeenTerm": "115000081"
    },
    {
      "combo": [
        15,
        18
      ],
      "count": 22,
      "weightedScore": 0.21290364718828958,
      "gap": 77,
      "lastSeenTerm": "115000060"
    },
    {
      "combo": [
        15,
        19
      ],
      "count": 13,
      "weightedScore": 0.21109409432979803,
      "gap": 65,
      "lastSeenTerm": "115000072"
    },
    {
      "combo": [
        22,
        35
      ],
      "count": 17,
      "weightedScore": 0.210483414724417,
      "gap": 68,
      "lastSeenTerm": "115000069"
    },
    {
      "combo": [
        19,
        27
      ],
      "count": 15,
      "weightedScore": 0.20828684354264526,
      "gap": 69,
      "lastSeenTerm": "115000068"
    },
    {
      "combo": [
        8,
        10
      ],
      "count": 14,
      "weightedScore": 0.20732662142341662,
      "gap": 71,
      "lastSeenTerm": "115000066"
    },
    {
      "combo": [
        23,
        37
      ],
      "count": 11,
      "weightedScore": 0.20513063900819833,
      "gap": 67,
      "lastSeenTerm": "115000070"
    },
    {
      "combo": [
        5,
        35
      ],
      "count": 14,
      "weightedScore": 0.20349014741844224,
      "gap": 73,
      "lastSeenTerm": "115000064"
    },
    {
      "combo": [
        10,
        13
      ],
      "count": 13,
      "weightedScore": 0.20329151091800673,
      "gap": 56,
      "lastSeenTerm": "115000081"
    },
    {
      "combo": [
        3,
        27
      ],
      "count": 23,
      "weightedScore": 0.20253279561312165,
      "gap": 82,
      "lastSeenTerm": "115000055"
    },
    {
      "combo": [
        13,
        27
      ],
      "count": 12,
      "weightedScore": 0.20251233954055906,
      "gap": 69,
      "lastSeenTerm": "115000068"
    },
    {
      "combo": [
        11,
        27
      ],
      "count": 19,
      "weightedScore": 0.2020111992806336,
      "gap": 69,
      "lastSeenTerm": "115000068"
    },
    {
      "combo": [
        13,
        31
      ],
      "count": 12,
      "weightedScore": 0.2018562198533516,
      "gap": 62,
      "lastSeenTerm": "115000075"
    },
    {
      "combo": [
        4,
        25
      ],
      "count": 15,
      "weightedScore": 0.2016115213649996,
      "gap": 53,
      "lastSeenTerm": "115000084"
    },
    {
      "combo": [
        31,
        33
      ],
      "count": 10,
      "weightedScore": 0.20032712435791433,
      "gap": 62,
      "lastSeenTerm": "115000075"
    },
    {
      "combo": [
        4,
        23
      ],
      "count": 15,
      "weightedScore": 0.19717307556016517,
      "gap": 73,
      "lastSeenTerm": "115000064"
    },
    {
      "combo": [
        29,
        36
      ],
      "count": 13,
      "weightedScore": 0.19689730699967928,
      "gap": 63,
      "lastSeenTerm": "115000074"
    },
    {
      "combo": [
        6,
        17
      ],
      "count": 10,
      "weightedScore": 0.1965384081214408,
      "gap": 59,
      "lastSeenTerm": "115000078"
    },
    {
      "combo": [
        16,
        39
      ],
      "count": 14,
      "weightedScore": 0.19468719323729794,
      "gap": 57,
      "lastSeenTerm": "115000080"
    },
    {
      "combo": [
        10,
        29
      ],
      "count": 9,
      "weightedScore": 0.19330071299661766,
      "gap": 63,
      "lastSeenTerm": "115000074"
    },
    {
      "combo": [
        1,
        9
      ],
      "count": 16,
      "weightedScore": 0.19229995087496513,
      "gap": 55,
      "lastSeenTerm": "115000082"
    },
    {
      "combo": [
        9,
        18
      ],
      "count": 14,
      "weightedScore": 0.18971582506490978,
      "gap": 55,
      "lastSeenTerm": "115000082"
    },
    {
      "combo": [
        19,
        32
      ],
      "count": 12,
      "weightedScore": 0.1887699682805008,
      "gap": 78,
      "lastSeenTerm": "115000059"
    },
    {
      "combo": [
        13,
        22
      ],
      "count": 15,
      "weightedScore": 0.18868739486699448,
      "gap": 69,
      "lastSeenTerm": "115000068"
    },
    {
      "combo": [
        10,
        28
      ],
      "count": 18,
      "weightedScore": 0.18458997752095696,
      "gap": 63,
      "lastSeenTerm": "115000074"
    },
    {
      "combo": [
        18,
        24
      ],
      "count": 13,
      "weightedScore": 0.18437424634704716,
      "gap": 60,
      "lastSeenTerm": "115000077"
    },
    {
      "combo": [
        12,
        27
      ],
      "count": 18,
      "weightedScore": 0.18022198202174783,
      "gap": 82,
      "lastSeenTerm": "115000055"
    },
    {
      "combo": [
        3,
        12
      ],
      "count": 15,
      "weightedScore": 0.18014149926832834,
      "gap": 82,
      "lastSeenTerm": "115000055"
    },
    {
      "combo": [
        12,
        29
      ],
      "count": 15,
      "weightedScore": 0.17820891551090332,
      "gap": 64,
      "lastSeenTerm": "115000073"
    },
    {
      "combo": [
        33,
        36
      ],
      "count": 18,
      "weightedScore": 0.17755792303199464,
      "gap": 62,
      "lastSeenTerm": "115000075"
    },
    {
      "combo": [
        11,
        16
      ],
      "count": 11,
      "weightedScore": 0.17474613148348456,
      "gap": 59,
      "lastSeenTerm": "115000078"
    },
    {
      "combo": [
        3,
        15
      ],
      "count": 13,
      "weightedScore": 0.17267322876202174,
      "gap": 66,
      "lastSeenTerm": "115000071"
    },
    {
      "combo": [
        23,
        30
      ],
      "count": 11,
      "weightedScore": 0.1716654768958351,
      "gap": 67,
      "lastSeenTerm": "115000070"
    },
    {
      "combo": [
        14,
        22
      ],
      "count": 18,
      "weightedScore": 0.1714893806920736,
      "gap": 65,
      "lastSeenTerm": "115000072"
    },
    {
      "combo": [
        17,
        29
      ],
      "count": 9,
      "weightedScore": 0.1705424883746982,
      "gap": 70,
      "lastSeenTerm": "115000067"
    },
    {
      "combo": [
        31,
        35
      ],
      "count": 15,
      "weightedScore": 0.17030751465879,
      "gap": 68,
      "lastSeenTerm": "115000069"
    },
    {
      "combo": [
        20,
        37
      ],
      "count": 14,
      "weightedScore": 0.16824892730674199,
      "gap": 61,
      "lastSeenTerm": "115000076"
    },
    {
      "combo": [
        14,
        15
      ],
      "count": 14,
      "weightedScore": 0.1653220092569958,
      "gap": 65,
      "lastSeenTerm": "115000072"
    },
    {
      "combo": [
        22,
        23
      ],
      "count": 13,
      "weightedScore": 0.16467450187810045,
      "gap": 85,
      "lastSeenTerm": "115000052"
    },
    {
      "combo": [
        20,
        24
      ],
      "count": 10,
      "weightedScore": 0.16300043081994087,
      "gap": 61,
      "lastSeenTerm": "115000076"
    },
    {
      "combo": [
        14,
        24
      ],
      "count": 15,
      "weightedScore": 0.16130160394742044,
      "gap": 61,
      "lastSeenTerm": "115000076"
    },
    {
      "combo": [
        12,
        16
      ],
      "count": 17,
      "weightedScore": 0.16073919673314227,
      "gap": 80,
      "lastSeenTerm": "115000057"
    },
    {
      "combo": [
        13,
        33
      ],
      "count": 15,
      "weightedScore": 0.15729349565415726,
      "gap": 62,
      "lastSeenTerm": "115000075"
    },
    {
      "combo": [
        7,
        19
      ],
      "count": 11,
      "weightedScore": 0.15728523738282837,
      "gap": 65,
      "lastSeenTerm": "115000072"
    },
    {
      "combo": [
        17,
        37
      ],
      "count": 11,
      "weightedScore": 0.15606680534366268,
      "gap": 61,
      "lastSeenTerm": "115000076"
    },
    {
      "combo": [
        17,
        20
      ],
      "count": 7,
      "weightedScore": 0.1559845352666019,
      "gap": 61,
      "lastSeenTerm": "115000076"
    },
    {
      "combo": [
        19,
        25
      ],
      "count": 11,
      "weightedScore": 0.15514293382359426,
      "gap": 91,
      "lastSeenTerm": "115000046"
    },
    {
      "combo": [
        20,
        29
      ],
      "count": 12,
      "weightedScore": 0.15451845759631402,
      "gap": 63,
      "lastSeenTerm": "115000074"
    },
    {
      "combo": [
        1,
        8
      ],
      "count": 10,
      "weightedScore": 0.15274927232355834,
      "gap": 79,
      "lastSeenTerm": "115000058"
    },
    {
      "combo": [
        28,
        29
      ],
      "count": 12,
      "weightedScore": 0.15261164498268454,
      "gap": 63,
      "lastSeenTerm": "115000074"
    },
    {
      "combo": [
        5,
        11
      ],
      "count": 17,
      "weightedScore": 0.14996852926550688,
      "gap": 72,
      "lastSeenTerm": "115000065"
    },
    {
      "combo": [
        15,
        39
      ],
      "count": 13,
      "weightedScore": 0.14674629511187476,
      "gap": 66,
      "lastSeenTerm": "115000071"
    },
    {
      "combo": [
        15,
        29
      ],
      "count": 18,
      "weightedScore": 0.14568786732656833,
      "gap": 83,
      "lastSeenTerm": "115000054"
    },
    {
      "combo": [
        22,
        31
      ],
      "count": 10,
      "weightedScore": 0.14483953842388547,
      "gap": 68,
      "lastSeenTerm": "115000069"
    },
    {
      "combo": [
        17,
        18
      ],
      "count": 14,
      "weightedScore": 0.14325200478677758,
      "gap": 77,
      "lastSeenTerm": "115000060"
    },
    {
      "combo": [
        25,
        37
      ],
      "count": 16,
      "weightedScore": 0.1409531729819662,
      "gap": 67,
      "lastSeenTerm": "115000070"
    },
    {
      "combo": [
        17,
        19
      ],
      "count": 13,
      "weightedScore": 0.14022569717133215,
      "gap": 70,
      "lastSeenTerm": "115000067"
    },
    {
      "combo": [
        33,
        39
      ],
      "count": 10,
      "weightedScore": 0.13898564005357134,
      "gap": 66,
      "lastSeenTerm": "115000071"
    },
    {
      "combo": [
        15,
        22
      ],
      "count": 8,
      "weightedScore": 0.13852670636445805,
      "gap": 65,
      "lastSeenTerm": "115000072"
    },
    {
      "combo": [
        32,
        34
      ],
      "count": 19,
      "weightedScore": 0.1363907677062678,
      "gap": 78,
      "lastSeenTerm": "115000059"
    },
    {
      "combo": [
        15,
        26
      ],
      "count": 13,
      "weightedScore": 0.13566638117330604,
      "gap": 74,
      "lastSeenTerm": "115000063"
    },
    {
      "combo": [
        17,
        32
      ],
      "count": 11,
      "weightedScore": 0.13543598259095127,
      "gap": 75,
      "lastSeenTerm": "115000062"
    },
    {
      "combo": [
        29,
        32
      ],
      "count": 10,
      "weightedScore": 0.13475832921419456,
      "gap": 78,
      "lastSeenTerm": "115000059"
    },
    {
      "combo": [
        10,
        18
      ],
      "count": 7,
      "weightedScore": 0.13400135027423277,
      "gap": 71,
      "lastSeenTerm": "115000066"
    },
    {
      "combo": [
        5,
        30
      ],
      "count": 9,
      "weightedScore": 0.13074829746939245,
      "gap": 67,
      "lastSeenTerm": "115000070"
    },
    {
      "combo": [
        5,
        25
      ],
      "count": 8,
      "weightedScore": 0.13060862906147264,
      "gap": 67,
      "lastSeenTerm": "115000070"
    },
    {
      "combo": [
        1,
        37
      ],
      "count": 20,
      "weightedScore": 0.13029669277069195,
      "gap": 85,
      "lastSeenTerm": "115000052"
    },
    {
      "combo": [
        26,
        38
      ],
      "count": 9,
      "weightedScore": 0.12723974690736178,
      "gap": 74,
      "lastSeenTerm": "115000063"
    },
    {
      "combo": [
        4,
        7
      ],
      "count": 14,
      "weightedScore": 0.12572472147085,
      "gap": 73,
      "lastSeenTerm": "115000064"
    },
    {
      "combo": [
        12,
        14
      ],
      "count": 17,
      "weightedScore": 0.12516388467682069,
      "gap": 75,
      "lastSeenTerm": "115000062"
    },
    {
      "combo": [
        10,
        12
      ],
      "count": 14,
      "weightedScore": 0.125115996018869,
      "gap": 89,
      "lastSeenTerm": "115000048"
    },
    {
      "combo": [
        23,
        32
      ],
      "count": 12,
      "weightedScore": 0.1250821796251672,
      "gap": 88,
      "lastSeenTerm": "115000049"
    },
    {
      "combo": [
        8,
        19
      ],
      "count": 18,
      "weightedScore": 0.12485061081448015,
      "gap": 91,
      "lastSeenTerm": "115000046"
    },
    {
      "combo": [
        8,
        13
      ],
      "count": 16,
      "weightedScore": 0.1235198886151504,
      "gap": 90,
      "lastSeenTerm": "115000047"
    },
    {
      "combo": [
        11,
        19
      ],
      "count": 12,
      "weightedScore": 0.12249618894274834,
      "gap": 69,
      "lastSeenTerm": "115000068"
    },
    {
      "combo": [
        22,
        28
      ],
      "count": 9,
      "weightedScore": 0.12240576780216934,
      "gap": 87,
      "lastSeenTerm": "115000050"
    },
    {
      "combo": [
        13,
        19
      ],
      "count": 10,
      "weightedScore": 0.12227595763577492,
      "gap": 69,
      "lastSeenTerm": "115000068"
    }
  ]
}